{ "introduction_obj_list": 
	[
		{ "title" : "文教大学湘南キャンパス",
			"id" : 0,
			"image_file" : "thumnail_sample_300",
			"abstract" : "文教大学湘南キャンパスです．",
			"score" : 4.6,
			"image_file1" : "img101",
			"image_file2" :	"img102",
			"lat" :	"35.370173",
			"lng" : "139.415208",
			"detail" : "文教大学湘南キャンパスでは，四季折々の豊かな自然の表情に囲まれ，落ち着いた雰囲気で勉学に励む環境が整っています．<br />春は，バス停からのアプローチや貯水池沿いの桜が新入生を迎え，赤レンガ色の建物に囲まれた中庭では，新緑から秋の紅葉，時々雪が学生の様子を見守ります．<br />途中改行を入れる場合は&lt;br /&gt;タグを用いる．<br />"
		},
		{ "title" : "2つめの詳細ページ",
			"id" : 1,
			"image_file" : "thumnail_sample_300",
			"abstract" : "2つめの詳細ページです．",
			"score" : 4.0,
			"image_file1" : "",
			"image_file2" :	"",
			"lat" :	"35.3732035",
			"lng" : "139.4184921",
			"detail" : "2つめ以降の詳細ページのデータは，１つめのオブジェクト（まとまり）の後に,（カンマ）を入れて，追加していきます．"
		},
		{ "title" : "ホーム",
			"id" : 2,
			"image_file" : "Home",
			"abstract" : "横浜市新生活応援サイト",
			"score" : 4.0,
			"image_file1" : "Home",
			"image_file2" :	"",
			"lat" :	"35.3732035",
			"lng" : "139.4184921",
			"detail" : "",
                        "bone" : "",
                        "btwo" : "",
                        "bthree" : "",
                        "bfour" : "",
                        "bfive" : "横浜市で新生活送るあなたを応援",
			"link" : ""
		},
		{ "title" : "神奈川区役所",
			"id" : 3,
			"image_file" : "Kuyaku",
			"abstract" : "ここで転入届やマイナンバーカードの更新ができます",
			"score" : 4.0,
			"image_file1" : "Kuyaku",
			"image_file2" :	"Kuyaku_thum",
			"lat" :	"35.4773968",
			"lng" : "139.6291242",
			"detail" : "〒221-0824 神奈川県横浜市神奈川区広台太田町3番地の8<br/>電話番号:045-411-7171",
                        "bone" : "開庁時間:月曜から金曜午前8時45分から午後5時まで<br/>※祝日休日12月29日から1月3日を除く<br/>転居届・転出届け・転入届けやマイナンバーカードの更新ができます。<br/>また、印鑑登録の住所変更・国民健康保険の住所変更・国民年金の住所変更・児童手当・保育園・幼稚園の転園手続き・ペットの登録などできることは多岐に渡ります。<br/>自分に必要な手続きをしっかり確認してから区役所に行くようにしましょう。",
                        "btwo" : "",
                        "bthree" : "",
                        "bfour" : "",
                        "bfive" : "",
			"link" : ""
		},
		{ "title" : "横浜市水道局",
			"id" : 4,
			"image_file" : "Suidou",
			"abstract" : "水道に関する手続きはこちらへ",
			"score" : 4.0,
			"image_file1" : "Suidou",
			"image_file2" :	"",
			"lat" :	"35.3739243",
			"lng" : "139.3755564",
			"detail" : "〒231-0005 神奈川県横浜市中区本町6丁目50番地の10<br/>電話番号:045-847-6262",
                        "bone" : "上記のリンクから水道の手続きの詳しい説明があります。<br/>新居での水道の使用開始手続きは、引越し日の3～4日前を目安に、水道局に連絡して行います。 手続きの方法は、主にインターネット・電話・郵送のいずれかでできます。 郵送に必要な水道使用開始申込書は、新居の郵便ポストや玄関に置かれていることが多いです。",
                        "btwo" : "",
                        "bthree" : "",
                        "bfour" : "",
                        "bfive" : "",
			"link" : "<a href=\"https://www.city.yokohama.lg.jp/kurashi/sumai-kurashi/suido-gesui/suido/\">テスト</a>"
		},
		{ "title" : "横浜中央郵便局",
			"id" : 5,
			"image_file" : "Yuubin",
			"abstract" : "郵便サービスについて",
			"score" : 4.0,
			"image_file1" : "Yuubin",
			"image_file2" :	"",
			"lat" :	"35.4646102",
			"lng" : "139.6225958",
			"detail" : "〒220-8799　神奈川県横浜市西区高島2丁目14番地の2<br/>電話番号:0570-943-212",
                        "bone" : "引越しの際には、郵便局にも住所を変更した旨を伝える必要があります。そのときに必要なのが転居届です。これを提出しておくと、無料で「転居・転送サービス」を受けることができます。古い住所宛ての手紙や荷物などの郵便物を、現在住んでいる新しい住所に転送してくれるサービスなので、必ず行いましょう。<br/>転居転送サービスを利用するには、まずインターネットか郵便窓口で手続きが必要です。<br/>提出者の本人確認書類（運転免許証や保険証など）<br/>転居前の住所が記載されていて確認できるもの（運転免許証やパスポート、住民票など、政府などが発行した書類の2点が必要になります。<br/>インターネットで手続きを行う際にはこちらの日本郵便のホームページから申し込みできます。",
                        "btwo" : "",
                        "bthree" : "",
                        "bfour" : "",
                        "bfive" : "",
			"link" : ""
		},
		{ "title" : "新生活始める時にやること持ち物リスト",
			"id" : 6,
			"image_file" : "List",
			"abstract" : "",
			"score" : 4.0,
			"image_file1" : "List",
			"image_file2" :	"",
			"lat" :	"",
			"lng" : "",
			"detail" : "高い・神奈川区役所に行く！やること 転居/転入届 マイナンバー更新 etc… 持ち物 本人確認書類印鑑 国民健康保険被保険者証<br/>・横浜市水道局に連絡！やること 水道利用開始の手続き 持ち物 郵送なら水道利用開始申請書<br/>・横浜郵便局に行く！やること 転居届の提出 持ち物 転居届<br/>・ご近所へのご挨拶と手土産（賃貸の場合は貸主にも）<br/>・運転免許証の住所変更<br/>・自動車の登録変更・車庫証明の発行<br/>・バイクの登録変更<br/>・飼い犬の登録<br/>・パスポートの手続き（本籍を変更した場合）<br/>",
                        "bone" : "",
                        "btwo" : "",
                        "bthree" : "",
                        "bfour" : "",
                        "bfive" : "",
			"link" : ""
		}
	]
}
